LICENSE
MANIFEST.in
README.rst
setup.py
mapcombine/__init__.py
mapcombine/_version.py
mapcombine/core.py
mapcombine.egg-info/PKG-INFO
mapcombine.egg-info/SOURCES.txt
mapcombine.egg-info/dependency_links.txt
mapcombine.egg-info/top_level.txt
mapcombine.egg-info/zip-safe