Metadata-Version: 1.0
Name: mapcombine
Version: 0.0.4
Summary: Simple combine-centric MapReduce
Home-page: http://github.com/maxhutch/mapcombine/
Author: Max Hutchinson
Author-email: maxhutch@gmail.com
License: MIT
Keywords: MapReduce
Platform: UNKNOWN
